testing_gc1983/__init__.py
testing_gc1983/main.py
testing_gc1983-0.0.7.dist-info/LICENSE
testing_gc1983-0.0.7.dist-info/METADATA
testing_gc1983-0.0.7.dist-info/WHEEL
testing_gc1983-0.0.7.dist-info/top_level.txt
testing_gc1983-0.0.7.dist-info/RECORD
