Metadata-Version: 2.1
Name: testing-gc1983
Version: 0.0.7
Summary: Testing packaging scenarios.
Home-page: https://github.com/pypa/sampleproject
Author: Gregory Coyle
Author-email: gregory.coyle@tufts.edu
License: UNKNOWN
Platform: UNKNOWN
Classifier: Programming Language :: Python :: 3
Classifier: License :: OSI Approved :: MIT License
Classifier: Operating System :: OS Independent
Requires-Python: >=3.6
Requires-Dist: jupyterlab (>=2.1.5)
